{
  "projectFullName": "newrelic/nr1-metrics-aggregator",
  "issues": {
    "open": 0
  },
  "releases": 2,
  "latestRelease": {
    "name": "v0.9.7",
    "date": "2020-06-05T15:58:06Z"
  },
  "commits": 89,
  "lastSixMonthsCommitTotal": 89,
  "contributors": 7,
  "pullRequests": {
    "open": 0
  },
  "searchCategory": "good first issue",
  "cachedIssues": [],
  "cachedContributors": [
    {
      "id": 32174276,
      "login": "semantic-release-bot",
      "avatarUrl": "https://avatars1.githubusercontent.com/u/32174276?v=4",
      "htmlUrl": "https://github.com/semantic-release-bot",
      "contributions": 1
    },
    {
      "id": 12127,
      "login": "WardCunningham",
      "avatarUrl": "https://avatars3.githubusercontent.com/u/12127?v=4",
      "htmlUrl": "https://github.com/WardCunningham",
      "contributions": 1
    },
    {
      "id": 13436647,
      "login": "psimkins",
      "avatarUrl": "https://avatars2.githubusercontent.com/u/13436647?v=4",
      "htmlUrl": "https://github.com/psimkins",
      "contributions": 2
    },
    {
      "id": 66321197,
      "login": "nr-opensource-bot",
      "avatarUrl": "https://avatars0.githubusercontent.com/u/66321197?v=4",
      "htmlUrl": "https://github.com/nr-opensource-bot",
      "contributions": 5
    },
    {
      "id": 6722433,
      "login": "jbeveland27",
      "avatarUrl": "https://avatars3.githubusercontent.com/u/6722433?v=4",
      "htmlUrl": "https://github.com/jbeveland27",
      "contributions": 6
    },
    {
      "id": 929261,
      "login": "tangollama",
      "avatarUrl": "https://avatars0.githubusercontent.com/u/929261?v=4",
      "htmlUrl": "https://github.com/tangollama",
      "contributions": 26
    },
    {
      "id": 53268450,
      "login": "jake-codes",
      "avatarUrl": "https://avatars3.githubusercontent.com/u/53268450?v=4",
      "htmlUrl": "https://github.com/jake-codes",
      "contributions": 30
    }
  ],
  "languages": [
    {
      "id": "MDg6TGFuZ3VhZ2UxNDA=",
      "name": "JavaScript",
      "color": "#f1e05a"
    },
    {
      "id": "MDg6TGFuZ3VhZ2UzMDg=",
      "name": "CSS",
      "color": "#563d7c"
    }
  ],
  "screenshots": [
    "https://raw.githubusercontent.com/newrelic/nr1-metrics-aggregator/master/catalog/screenshots/nr1-metrics-aggregator-1.png",
    "https://raw.githubusercontent.com/newrelic/nr1-metrics-aggregator/master/catalog/screenshots/nr1-metrics-aggregator-2.png"
  ],
  "license": {
    "id": "MDc6TGljZW5zZTI=",
    "name": "Apache License 2.0",
    "spdxId": "Apache-2.0",
    "url": "http://choosealicense.com/licenses/apache-2.0/",
    "featured": true,
    "key": "apache-2.0"
  }
}