{
  "projectFullName": "newrelic/newrelic-oss-cli",
  "issues": {
    "open": 0
  },
  "releases": 0,
  "commits": 29,
  "contributors": 1,
  "pullRequests": {
    "open": 0
  },
  "searchCategory": "good first issue",
  "cachedIssues": [],
  "cachedContributors": [
    {
      "id": 197140,
      "login": "devfreddy",
      "avatarUrl": "https://avatars1.githubusercontent.com/u/197140?v=4",
      "htmlUrl": "https://github.com/devfreddy",
      "contributions": 28
    }
  ],
  "languages": [
    {
      "id": "MDg6TGFuZ3VhZ2UxNDA=",
      "name": "JavaScript",
      "color": "#f1e05a"
    },
    {
      "id": "MDg6TGFuZ3VhZ2U0NjM=",
      "name": "Batchfile",
      "color": "#C1F12E"
    }
  ],
  "screenshots": [
    "https://raw.githubusercontent.com/newrelic/newrelic-oss-cli/master/screenshots/.gitkeep"
  ]
}