{
  "projectFullName": "newrelic-experimental/nr-find-log4j",
  "issues": {
    "open": 2
  },
  "releases": 0,
  "latestRelease": null,
  "commits": 35,
  "lastSixMonthsCommitTotal": 35,
  "contributors": 4,
  "pullRequests": {
    "open": 1
  },
  "searchCategory": "good first issue",
  "cachedIssues": [],
  "cachedContributors": [
    {
      "id": 55462,
      "login": "mattbaker",
      "avatarUrl": "https://avatars.githubusercontent.com/u/55462?v=4",
      "htmlUrl": "https://github.com/mattbaker",
      "contributions": 1
    },
    {
      "id": 10755607,
      "login": "karl-barbour",
      "avatarUrl": "https://avatars.githubusercontent.com/u/10755607?v=4",
      "htmlUrl": "https://github.com/karl-barbour",
      "contributions": 3
    },
    {
      "id": 4061375,
      "login": "ricegi",
      "avatarUrl": "https://avatars.githubusercontent.com/u/4061375?v=4",
      "htmlUrl": "https://github.com/ricegi",
      "contributions": 1
    },
    {
      "id": 482671,
      "login": "fightingmonk",
      "avatarUrl": "https://avatars.githubusercontent.com/u/482671?v=4",
      "htmlUrl": "https://github.com/fightingmonk",
      "contributions": 22
    }
  ],
  "languages": [
    {
      "id": "MDg6TGFuZ3VhZ2UxNDA=",
      "name": "JavaScript",
      "color": "#f1e05a"
    }
  ],
  "screenshots": [],
  "license": {
    "id": "MDc6TGljZW5zZTI=",
    "name": "Apache License 2.0",
    "spdxId": "Apache-2.0",
    "url": "http://choosealicense.com/licenses/apache-2.0/",
    "featured": true,
    "key": "apache-2.0"
  }
}