{
  "projectFullName": "newrelic-experimental/nr1-ingest-metric-script",
  "issues": {
    "open": 0
  },
  "releases": 0,
  "latestRelease": null,
  "commits": 24,
  "lastSixMonthsCommitTotal": 24,
  "contributors": 2,
  "pullRequests": {
    "open": 0
  },
  "searchCategory": "good first issue",
  "cachedIssues": [],
  "cachedContributors": [
    {
      "id": 43244625,
      "login": "melissaklein24",
      "avatarUrl": "https://avatars.githubusercontent.com/u/43244625?v=4",
      "htmlUrl": "https://github.com/melissaklein24",
      "contributions": 1
    },
    {
      "id": 68360819,
      "login": "umanorapracadadia",
      "avatarUrl": "https://avatars.githubusercontent.com/u/68360819?v=4",
      "htmlUrl": "https://github.com/umanorapracadadia",
      "contributions": 23
    }
  ],
  "languages": [
    {
      "id": "MDg6TGFuZ3VhZ2UxNDA=",
      "name": "JavaScript",
      "color": "#f1e05a"
    }
  ],
  "screenshots": [],
  "license": {
    "id": "MDc6TGljZW5zZTI=",
    "name": "Apache License 2.0",
    "spdxId": "Apache-2.0",
    "url": "http://choosealicense.com/licenses/apache-2.0/",
    "featured": true,
    "key": "apache-2.0"
  }
}