{
  "projectFullName": "newrelic/fluentbit-examples",
  "issues": {
    "open": 0
  },
  "releases": 0,
  "latestRelease": null,
  "commits": 7,
  "contributors": 1,
  "pullRequests": {
    "open": 0
  },
  "searchCategory": "good first issue",
  "cachedIssues": [],
  "cachedContributors": [
    {
      "id": 55508447,
      "login": "mculmone",
      "avatarUrl": "https://avatars2.githubusercontent.com/u/55508447?v=4",
      "htmlUrl": "https://github.com/mculmone",
      "contributions": 7
    }
  ],
  "languages": [],
  "screenshots": [],
  "license": null
}