{
  "projectFullName": "newrelic/newrelic-lambda-cli",
  "issues": {
    "open": 11
  },
  "releases": 66,
  "latestRelease": {
    "name": "v0.7.0",
    "date": "2022-03-17T21:56:48Z"
  },
  "commits": 390,
  "lastSixMonthsCommitTotal": 13,
  "contributors": 20,
  "pullRequests": {
    "open": 0
  },
  "searchCategory": "good first issue",
  "cachedIssues": [],
  "cachedContributors": [
    {
      "id": 7001514,
      "login": "bmcfeely",
      "avatarUrl": "https://avatars.githubusercontent.com/u/7001514?v=4",
      "htmlUrl": "https://github.com/bmcfeely",
      "contributions": 2
    },
    {
      "id": 11327,
      "login": "mrickard",
      "avatarUrl": "https://avatars.githubusercontent.com/u/11327?v=4",
      "htmlUrl": "https://github.com/mrickard",
      "contributions": 7
    },
    {
      "id": 61292402,
      "login": "keegoid-nr",
      "avatarUrl": "https://avatars.githubusercontent.com/u/61292402?v=4",
      "htmlUrl": "https://github.com/keegoid-nr",
      "contributions": 3
    },
    {
      "id": 4206754,
      "login": "Gene5ive",
      "avatarUrl": "https://avatars.githubusercontent.com/u/4206754?v=4",
      "htmlUrl": "https://github.com/Gene5ive",
      "contributions": 2
    },
    {
      "id": 17498,
      "login": "kolanos",
      "avatarUrl": "https://avatars.githubusercontent.com/u/17498?v=4",
      "htmlUrl": "https://github.com/kolanos",
      "contributions": 143
    },
    {
      "id": 62742678,
      "login": "Kavinraja-G",
      "avatarUrl": "https://avatars.githubusercontent.com/u/62742678?v=4",
      "htmlUrl": "https://github.com/Kavinraja-G",
      "contributions": 1
    },
    {
      "id": 1900941,
      "login": "Menghongli",
      "avatarUrl": "https://avatars.githubusercontent.com/u/1900941?v=4",
      "htmlUrl": "https://github.com/Menghongli",
      "contributions": 1
    },
    {
      "id": 13453208,
      "login": "ismferd",
      "avatarUrl": "https://avatars.githubusercontent.com/u/13453208?v=4",
      "htmlUrl": "https://github.com/ismferd",
      "contributions": 2
    },
    {
      "id": 28942544,
      "login": "katiewest820",
      "avatarUrl": "https://avatars.githubusercontent.com/u/28942544?v=4",
      "htmlUrl": "https://github.com/katiewest820",
      "contributions": 7
    },
    {
      "id": 5370752,
      "login": "irishgordo",
      "avatarUrl": "https://avatars.githubusercontent.com/u/5370752?v=4",
      "htmlUrl": "https://github.com/irishgordo",
      "contributions": 2
    },
    {
      "id": 585473,
      "login": "MattWhelan",
      "avatarUrl": "https://avatars.githubusercontent.com/u/585473?v=4",
      "htmlUrl": "https://github.com/MattWhelan",
      "contributions": 28
    },
    {
      "id": 8593135,
      "login": "katiebayes",
      "avatarUrl": "https://avatars.githubusercontent.com/u/8593135?v=4",
      "htmlUrl": "https://github.com/katiebayes",
      "contributions": 2
    },
    {
      "id": 284537,
      "login": "HiDAl",
      "avatarUrl": "https://avatars.githubusercontent.com/u/284537?v=4",
      "htmlUrl": "https://github.com/HiDAl",
      "contributions": 1
    },
    {
      "id": 43244625,
      "login": "melissaklein24",
      "avatarUrl": "https://avatars.githubusercontent.com/u/43244625?v=4",
      "htmlUrl": "https://github.com/melissaklein24",
      "contributions": 2
    },
    {
      "id": 3925334,
      "login": "salvatorious",
      "avatarUrl": "https://avatars.githubusercontent.com/u/3925334?v=4",
      "htmlUrl": "https://github.com/salvatorious",
      "contributions": 14
    },
    {
      "id": 73207,
      "login": "ewindisch",
      "avatarUrl": "https://avatars.githubusercontent.com/u/73207?v=4",
      "htmlUrl": "https://github.com/ewindisch",
      "contributions": 67
    },
    {
      "id": 55114125,
      "login": "hmacdonald-nr",
      "avatarUrl": "https://avatars.githubusercontent.com/u/55114125?v=4",
      "htmlUrl": "https://github.com/hmacdonald-nr",
      "contributions": 4
    },
    {
      "id": 657586,
      "login": "igoratron",
      "avatarUrl": "https://avatars.githubusercontent.com/u/657586?v=4",
      "htmlUrl": "https://github.com/igoratron",
      "contributions": 1
    },
    {
      "id": 10356311,
      "login": "ppatelcodal",
      "avatarUrl": "https://avatars.githubusercontent.com/u/10356311?v=4",
      "htmlUrl": "https://github.com/ppatelcodal",
      "contributions": 1
    },
    {
      "id": 73652669,
      "login": "arvdias",
      "avatarUrl": "https://avatars.githubusercontent.com/u/73652669?v=4",
      "htmlUrl": "https://github.com/arvdias",
      "contributions": 32
    }
  ],
  "languages": [
    {
      "id": "MDg6TGFuZ3VhZ2UxNDU=",
      "name": "Python",
      "color": "#3572A5"
    },
    {
      "id": "MDg6TGFuZ3VhZ2UxMzk=",
      "name": "Shell",
      "color": "#89e051"
    },
    {
      "id": "MDg6TGFuZ3VhZ2U1MzU=",
      "name": "Dockerfile",
      "color": "#384d54"
    }
  ],
  "screenshots": [],
  "license": {
    "id": "MDc6TGljZW5zZTI=",
    "name": "Apache License 2.0",
    "spdxId": "Apache-2.0",
    "url": "http://choosealicense.com/licenses/apache-2.0/",
    "featured": true,
    "key": "apache-2.0"
  }
}