{
  "projectFullName": "newrelic/docs-website",
  "issues": {
    "open": 20
  },
  "releases": 0,
  "latestRelease": null,
  "commits": 208,
  "lastSixMonthsCommitTotal": 208,
  "contributors": 6,
  "pullRequests": {
    "open": 3
  },
  "searchCategory": "good first issue",
  "cachedIssues": [],
  "cachedContributors": [
    {
      "id": 1395158,
      "login": "jpvajda",
      "avatarUrl": "https://avatars1.githubusercontent.com/u/1395158?v=4",
      "htmlUrl": "https://github.com/jpvajda",
      "contributions": 1
    },
    {
      "id": 197140,
      "login": "devfreddy",
      "avatarUrl": "https://avatars1.githubusercontent.com/u/197140?v=4",
      "htmlUrl": "https://github.com/devfreddy",
      "contributions": 1
    },
    {
      "id": 38332422,
      "login": "caylahamann",
      "avatarUrl": "https://avatars2.githubusercontent.com/u/38332422?v=4",
      "htmlUrl": "https://github.com/caylahamann",
      "contributions": 19
    },
    {
      "id": 2952843,
      "login": "roadlittledawn",
      "avatarUrl": "https://avatars3.githubusercontent.com/u/2952843?v=4",
      "htmlUrl": "https://github.com/roadlittledawn",
      "contributions": 26
    },
    {
      "id": 1946433,
      "login": "zstix",
      "avatarUrl": "https://avatars3.githubusercontent.com/u/1946433?v=4",
      "htmlUrl": "https://github.com/zstix",
      "contributions": 53
    },
    {
      "id": 565661,
      "login": "jerelmiller",
      "avatarUrl": "https://avatars2.githubusercontent.com/u/565661?v=4",
      "htmlUrl": "https://github.com/jerelmiller",
      "contributions": 71
    }
  ],
  "languages": [
    {
      "id": "MDg6TGFuZ3VhZ2UxNDA=",
      "name": "JavaScript",
      "color": "#f1e05a"
    }
  ],
  "screenshots": [],
  "license": {
    "id": "MDc6TGljZW5zZTI=",
    "name": "Apache License 2.0",
    "spdxId": "Apache-2.0",
    "url": "http://choosealicense.com/licenses/apache-2.0/",
    "featured": true,
    "key": "apache-2.0"
  }
}