{
  "projectFullName": "newrelic/FY23SKO-OaC",
  "issues": {
    "open": 1
  },
  "releases": 0,
  "latestRelease": null,
  "commits": 50,
  "lastSixMonthsCommitTotal": 24,
  "contributors": 7,
  "pullRequests": {
    "open": 0
  },
  "searchCategory": "good first issue",
  "cachedIssues": [],
  "cachedContributors": [
    {
      "id": 65086728,
      "login": "pnvnd",
      "avatarUrl": "https://avatars.githubusercontent.com/u/65086728?v=4",
      "htmlUrl": "https://github.com/pnvnd",
      "contributions": 1
    },
    {
      "id": 1172100,
      "login": "keithmorris",
      "avatarUrl": "https://avatars.githubusercontent.com/u/1172100?v=4",
      "htmlUrl": "https://github.com/keithmorris",
      "contributions": 1
    },
    {
      "id": 197140,
      "login": "devfreddy",
      "avatarUrl": "https://avatars.githubusercontent.com/u/197140?v=4",
      "htmlUrl": "https://github.com/devfreddy",
      "contributions": 1
    },
    {
      "id": 43244625,
      "login": "melissaklein24",
      "avatarUrl": "https://avatars.githubusercontent.com/u/43244625?v=4",
      "htmlUrl": "https://github.com/melissaklein24",
      "contributions": 1
    },
    {
      "id": 8005856,
      "login": "Bijesse",
      "avatarUrl": "https://avatars.githubusercontent.com/u/8005856?v=4",
      "htmlUrl": "https://github.com/Bijesse",
      "contributions": 2
    },
    {
      "id": 55132258,
      "login": "jsbnr",
      "avatarUrl": "https://avatars.githubusercontent.com/u/55132258?v=4",
      "htmlUrl": "https://github.com/jsbnr",
      "contributions": 18
    },
    {
      "id": 184273,
      "login": "kidk",
      "avatarUrl": "https://avatars.githubusercontent.com/u/184273?v=4",
      "htmlUrl": "https://github.com/kidk",
      "contributions": 20
    }
  ],
  "languages": [
    {
      "id": "MDg6TGFuZ3VhZ2UxMzk=",
      "name": "Shell",
      "color": "#89e051"
    },
    {
      "id": "MDg6TGFuZ3VhZ2U0Nzk=",
      "name": "HCL",
      "color": null
    }
  ],
  "screenshots": [],
  "license": {
    "id": "MDc6TGljZW5zZTI=",
    "name": "Apache License 2.0",
    "spdxId": "Apache-2.0",
    "url": "http://choosealicense.com/licenses/apache-2.0/",
    "featured": true,
    "key": "apache-2.0"
  }
}