{
  "projectFullName": "newrelic/minotaur",
  "issues": {
    "open": 0
  },
  "releases": 0,
  "latestRelease": null,
  "commits": 144,
  "contributors": 3,
  "pullRequests": {
    "open": 0
  },
  "searchCategory": "good first issue",
  "cachedIssues": [],
  "cachedContributors": [
    {
      "id": 139940,
      "login": "david-j-peterson",
      "avatarUrl": "https://avatars2.githubusercontent.com/u/139940?v=4",
      "htmlUrl": "https://github.com/david-j-peterson",
      "contributions": 2
    },
    {
      "id": 6145659,
      "login": "LLParse",
      "avatarUrl": "https://avatars2.githubusercontent.com/u/6145659?v=4",
      "htmlUrl": "https://github.com/LLParse",
      "contributions": 5
    },
    {
      "id": 115151,
      "login": "joestein",
      "avatarUrl": "https://avatars1.githubusercontent.com/u/115151?v=4",
      "htmlUrl": "https://github.com/joestein",
      "contributions": 18
    }
  ],
  "languages": [
    {
      "id": "MDg6TGFuZ3VhZ2UxMzk=",
      "name": "Shell",
      "color": "#89e051"
    },
    {
      "id": "MDg6TGFuZ3VhZ2UxNDU=",
      "name": "Python",
      "color": "#3572A5"
    },
    {
      "id": "MDg6TGFuZ3VhZ2UxNDE=",
      "name": "Ruby",
      "color": "#701516"
    },
    {
      "id": "MDg6TGFuZ3VhZ2U0MTc=",
      "name": "HTML",
      "color": "#e34c26"
    }
  ],
  "screenshots": []
}