{
  "projectFullName": "newrelic/deployment-marker-action",
  "issues": {
    "open": 3
  },
  "releases": 8,
  "latestRelease": {
    "name": "v2.0.0",
    "date": "2023-01-31T16:52:05Z"
  },
  "commits": 51,
  "lastSixMonthsCommitTotal": 3,
  "contributors": 6,
  "pullRequests": {
    "open": 0
  },
  "searchCategory": "good first issue",
  "cachedIssues": [],
  "cachedContributors": [
    {
      "id": 110412864,
      "login": "JustinLewisNR",
      "avatarUrl": "https://avatars.githubusercontent.com/u/110412864?v=4",
      "htmlUrl": "https://github.com/JustinLewisNR",
      "contributions": 1
    },
    {
      "id": 6873609,
      "login": "rizalgowandy",
      "avatarUrl": "https://avatars.githubusercontent.com/u/6873609?v=4",
      "htmlUrl": "https://github.com/rizalgowandy",
      "contributions": 1
    },
    {
      "id": 14275767,
      "login": "B0go",
      "avatarUrl": "https://avatars.githubusercontent.com/u/14275767?v=4",
      "htmlUrl": "https://github.com/B0go",
      "contributions": 2
    },
    {
      "id": 5859975,
      "login": "StephenGoodall",
      "avatarUrl": "https://avatars.githubusercontent.com/u/5859975?v=4",
      "htmlUrl": "https://github.com/StephenGoodall",
      "contributions": 4
    },
    {
      "id": 455419,
      "login": "jthurman42",
      "avatarUrl": "https://avatars.githubusercontent.com/u/455419?v=4",
      "htmlUrl": "https://github.com/jthurman42",
      "contributions": 13
    },
    {
      "id": 2590905,
      "login": "sanderblue",
      "avatarUrl": "https://avatars.githubusercontent.com/u/2590905?v=4",
      "htmlUrl": "https://github.com/sanderblue",
      "contributions": 17
    }
  ],
  "languages": [
    {
      "id": "MDg6TGFuZ3VhZ2U1MzU=",
      "name": "Dockerfile",
      "color": "#384d54"
    },
    {
      "id": "MDg6TGFuZ3VhZ2UxMzk=",
      "name": "Shell",
      "color": "#89e051"
    },
    {
      "id": "MDg6TGFuZ3VhZ2U0MDM=",
      "name": "Makefile",
      "color": "#427819"
    }
  ],
  "screenshots": [],
  "license": {
    "id": "MDc6TGljZW5zZTI=",
    "name": "Apache License 2.0",
    "spdxId": "Apache-2.0",
    "url": "http://choosealicense.com/licenses/apache-2.0/",
    "featured": true,
    "key": "apache-2.0"
  }
}