{
  "projectFullName": "newrelic/developer-website",
  "issues": {
    "open": 68
  },
  "releases": 68,
  "latestRelease": {
    "name": "v1.21.2",
    "date": "2020-09-24T13:55:42Z"
  },
  "commits": 2950,
  "lastSixMonthsCommitTotal": 2950,
  "contributors": 41,
  "pullRequests": {
    "open": 4
  },
  "searchCategory": "good first issue",
  "cachedIssues": [
    {
      "id": "MDU6SXNzdWU2NDExMDA5ODA=",
      "title": "Animated GIFs are not supported",
      "url": "https://github.com/newrelic/developer-website/issues/179",
      "createdAt": "2020-06-18T10:38:52Z",
      "comments": {
        "totalCount": 1
      },
      "author": {
        "login": "theletterf",
        "id": "MDQ6VXNlcjE3NzM2MTY=",
        "email": "",
        "name": "Fabrizio Ferri-Benedetti"
      },
      "number": 179,
      "createdBy": "Fabrizio Ferri-Benedetti"
    },
    {
      "id": "MDU6SXNzdWU2NDM0NDU2NzI=",
      "title": "Add space between final step and general text.",
      "url": "https://github.com/newrelic/developer-website/issues/219",
      "createdAt": "2020-06-23T00:42:21Z",
      "comments": {
        "totalCount": 0
      },
      "author": {
        "login": "rhetoric101",
        "id": "MDQ6VXNlcjE4MDQwMjc0",
        "email": "",
        "name": "Rob Siebens"
      },
      "number": 219,
      "createdBy": "Rob Siebens"
    },
    {
      "id": "MDU6SXNzdWU2NDQwODAzNjI=",
      "title": "Automatic code formatting is a bit too aggressive",
      "url": "https://github.com/newrelic/developer-website/issues/222",
      "createdAt": "2020-06-23T19:11:44Z",
      "comments": {
        "totalCount": 0
      },
      "author": {
        "login": "jerelmiller",
        "id": "MDQ6VXNlcjU2NTY2MQ==",
        "email": "",
        "name": "Jerel Miller"
      },
      "number": 222,
      "createdBy": "Jerel Miller"
    }
  ],
  "cachedContributors": [
    {
      "id": 57272374,
      "login": "thtmnisamnstr",
      "avatarUrl": "https://avatars3.githubusercontent.com/u/57272374?v=4",
      "htmlUrl": "https://github.com/thtmnisamnstr",
      "contributions": 1
    },
    {
      "id": 1187068,
      "login": "tariqahmed",
      "avatarUrl": "https://avatars0.githubusercontent.com/u/1187068?v=4",
      "htmlUrl": "https://github.com/tariqahmed",
      "contributions": 1
    },
    {
      "id": 2590905,
      "login": "sanderblue",
      "avatarUrl": "https://avatars2.githubusercontent.com/u/2590905?v=4",
      "htmlUrl": "https://github.com/sanderblue",
      "contributions": 1
    },
    {
      "id": 2952843,
      "login": "roadlittledawn",
      "avatarUrl": "https://avatars3.githubusercontent.com/u/2952843?v=4",
      "htmlUrl": "https://github.com/roadlittledawn",
      "contributions": 1
    },
    {
      "id": 4978846,
      "login": "rajatagarwal",
      "avatarUrl": "https://avatars2.githubusercontent.com/u/4978846?v=4",
      "htmlUrl": "https://github.com/rajatagarwal",
      "contributions": 1
    },
    {
      "id": 18387,
      "login": "mwlang",
      "avatarUrl": "https://avatars0.githubusercontent.com/u/18387?v=4",
      "htmlUrl": "https://github.com/mwlang",
      "contributions": 1
    },
    {
      "id": 1261626,
      "login": "mouradmourafiq",
      "avatarUrl": "https://avatars3.githubusercontent.com/u/1261626?v=4",
      "htmlUrl": "https://github.com/mouradmourafiq",
      "contributions": 1
    },
    {
      "id": 1663955,
      "login": "mbazhlekova",
      "avatarUrl": "https://avatars1.githubusercontent.com/u/1663955?v=4",
      "htmlUrl": "https://github.com/mbazhlekova",
      "contributions": 1
    },
    {
      "id": 558327,
      "login": "maju6406",
      "avatarUrl": "https://avatars3.githubusercontent.com/u/558327?v=4",
      "htmlUrl": "https://github.com/maju6406",
      "contributions": 1
    },
    {
      "id": 3792897,
      "login": "honeyd",
      "avatarUrl": "https://avatars2.githubusercontent.com/u/3792897?v=4",
      "htmlUrl": "https://github.com/honeyd",
      "contributions": 1
    },
    {
      "id": 67129743,
      "login": "dbarnesbrownNR",
      "avatarUrl": "https://avatars0.githubusercontent.com/u/67129743?v=4",
      "htmlUrl": "https://github.com/dbarnesbrownNR",
      "contributions": 1
    },
    {
      "id": 39946,
      "login": "binaryseed",
      "avatarUrl": "https://avatars1.githubusercontent.com/u/39946?v=4",
      "htmlUrl": "https://github.com/binaryseed",
      "contributions": 1
    },
    {
      "id": 70902571,
      "login": "acuestanewrelic",
      "avatarUrl": "https://avatars3.githubusercontent.com/u/70902571?v=4",
      "htmlUrl": "https://github.com/acuestanewrelic",
      "contributions": 1
    },
    {
      "id": 46462340,
      "login": "abuchanan-nr",
      "avatarUrl": "https://avatars2.githubusercontent.com/u/46462340?v=4",
      "htmlUrl": "https://github.com/abuchanan-nr",
      "contributions": 1
    },
    {
      "id": 20293876,
      "login": "tyreer",
      "avatarUrl": "https://avatars1.githubusercontent.com/u/20293876?v=4",
      "htmlUrl": "https://github.com/tyreer",
      "contributions": 2
    },
    {
      "id": 929261,
      "login": "tangollama",
      "avatarUrl": "https://avatars0.githubusercontent.com/u/929261?v=4",
      "htmlUrl": "https://github.com/tangollama",
      "contributions": 2
    },
    {
      "id": 413389,
      "login": "ctrombley",
      "avatarUrl": "https://avatars0.githubusercontent.com/u/413389?v=4",
      "htmlUrl": "https://github.com/ctrombley",
      "contributions": 2
    },
    {
      "id": 8672090,
      "login": "alexronquillo",
      "avatarUrl": "https://avatars1.githubusercontent.com/u/8672090?v=4",
      "htmlUrl": "https://github.com/alexronquillo",
      "contributions": 2
    },
    {
      "id": 42678939,
      "login": "bradleycamacho",
      "avatarUrl": "https://avatars1.githubusercontent.com/u/42678939?v=4",
      "htmlUrl": "https://github.com/bradleycamacho",
      "contributions": 3
    },
    {
      "id": 7992384,
      "login": "paperclypse",
      "avatarUrl": "https://avatars0.githubusercontent.com/u/7992384?v=4",
      "htmlUrl": "https://github.com/paperclypse",
      "contributions": 4
    },
    {
      "id": 1987319,
      "login": "idirouhab",
      "avatarUrl": "https://avatars1.githubusercontent.com/u/1987319?v=4",
      "htmlUrl": "https://github.com/idirouhab",
      "contributions": 4
    },
    {
      "id": 812989,
      "login": "danielgolden",
      "avatarUrl": "https://avatars2.githubusercontent.com/u/812989?v=4",
      "htmlUrl": "https://github.com/danielgolden",
      "contributions": 9
    },
    {
      "id": 270746,
      "login": "thejonanshow",
      "avatarUrl": "https://avatars3.githubusercontent.com/u/270746?v=4",
      "htmlUrl": "https://github.com/thejonanshow",
      "contributions": 12
    },
    {
      "id": 45029322,
      "login": "polfliet",
      "avatarUrl": "https://avatars2.githubusercontent.com/u/45029322?v=4",
      "htmlUrl": "https://github.com/polfliet",
      "contributions": 12
    },
    {
      "id": 6426523,
      "login": "veextee",
      "avatarUrl": "https://avatars3.githubusercontent.com/u/6426523?v=4",
      "htmlUrl": "https://github.com/veextee",
      "contributions": 15
    },
    {
      "id": 1773616,
      "login": "theletterf",
      "avatarUrl": "https://avatars3.githubusercontent.com/u/1773616?v=4",
      "htmlUrl": "https://github.com/theletterf",
      "contributions": 17
    },
    {
      "id": 522116,
      "login": "markweitzel",
      "avatarUrl": "https://avatars1.githubusercontent.com/u/522116?v=4",
      "htmlUrl": "https://github.com/markweitzel",
      "contributions": 26
    },
    {
      "id": 186715,
      "login": "djsauble",
      "avatarUrl": "https://avatars1.githubusercontent.com/u/186715?v=4",
      "htmlUrl": "https://github.com/djsauble",
      "contributions": 26
    },
    {
      "id": 22381983,
      "login": "meems1996",
      "avatarUrl": "https://avatars1.githubusercontent.com/u/22381983?v=4",
      "htmlUrl": "https://github.com/meems1996",
      "contributions": 32
    },
    {
      "id": 55004296,
      "login": "davidhou17",
      "avatarUrl": "https://avatars1.githubusercontent.com/u/55004296?v=4",
      "htmlUrl": "https://github.com/davidhou17",
      "contributions": 38
    },
    {
      "id": 18040274,
      "login": "rhetoric101",
      "avatarUrl": "https://avatars3.githubusercontent.com/u/18040274?v=4",
      "htmlUrl": "https://github.com/rhetoric101",
      "contributions": 48
    },
    {
      "id": 19733683,
      "login": "snyk-bot",
      "avatarUrl": "https://avatars2.githubusercontent.com/u/19733683?v=4",
      "htmlUrl": "https://github.com/snyk-bot",
      "contributions": 61
    },
    {
      "id": 3023056,
      "login": "timglaser",
      "avatarUrl": "https://avatars0.githubusercontent.com/u/3023056?v=4",
      "htmlUrl": "https://github.com/timglaser",
      "contributions": 74
    },
    {
      "id": 13562672,
      "login": "jaesius",
      "avatarUrl": "https://avatars3.githubusercontent.com/u/13562672?v=4",
      "htmlUrl": "https://github.com/jaesius",
      "contributions": 75
    },
    {
      "id": 38332422,
      "login": "caylahamann",
      "avatarUrl": "https://avatars2.githubusercontent.com/u/38332422?v=4",
      "htmlUrl": "https://github.com/caylahamann",
      "contributions": 114
    },
    {
      "id": 58010132,
      "login": "mmfred",
      "avatarUrl": "https://avatars0.githubusercontent.com/u/58010132?v=4",
      "htmlUrl": "https://github.com/mmfred",
      "contributions": 127
    },
    {
      "id": 66321197,
      "login": "nr-opensource-bot",
      "avatarUrl": "https://avatars0.githubusercontent.com/u/66321197?v=4",
      "htmlUrl": "https://github.com/nr-opensource-bot",
      "contributions": 128
    },
    {
      "id": 1395158,
      "login": "jpvajda",
      "avatarUrl": "https://avatars1.githubusercontent.com/u/1395158?v=4",
      "htmlUrl": "https://github.com/jpvajda",
      "contributions": 132
    },
    {
      "id": 39655074,
      "login": "LizBaker",
      "avatarUrl": "https://avatars1.githubusercontent.com/u/39655074?v=4",
      "htmlUrl": "https://github.com/LizBaker",
      "contributions": 159
    },
    {
      "id": 1946433,
      "login": "zstix",
      "avatarUrl": "https://avatars3.githubusercontent.com/u/1946433?v=4",
      "htmlUrl": "https://github.com/zstix",
      "contributions": 291
    },
    {
      "id": 565661,
      "login": "jerelmiller",
      "avatarUrl": "https://avatars2.githubusercontent.com/u/565661?v=4",
      "htmlUrl": "https://github.com/jerelmiller",
      "contributions": 776
    }
  ],
  "languages": [
    {
      "id": "MDg6TGFuZ3VhZ2UxNDA=",
      "name": "JavaScript",
      "color": "#f1e05a"
    },
    {
      "id": "MDg6TGFuZ3VhZ2U2MDU=",
      "name": "SCSS",
      "color": "#c6538c"
    }
  ],
  "screenshots": [],
  "license": {
    "id": "MDc6TGljZW5zZTI=",
    "name": "Apache License 2.0",
    "spdxId": "Apache-2.0",
    "url": "http://choosealicense.com/licenses/apache-2.0/",
    "featured": true,
    "key": "apache-2.0"
  }
}