{
  "projectFullName": "newrelic-experimental/nr-nr1viz-aligned-timeseries",
  "issues": {
    "open": 0
  },
  "releases": 0,
  "latestRelease": null,
  "commits": 3,
  "lastSixMonthsCommitTotal": 0,
  "contributors": 1,
  "pullRequests": {
    "open": 0
  },
  "searchCategory": "good first issue",
  "cachedIssues": [],
  "cachedContributors": [
    {
      "id": 55132258,
      "login": "jsbnr",
      "avatarUrl": "https://avatars.githubusercontent.com/u/55132258?v=4",
      "htmlUrl": "https://github.com/jsbnr",
      "contributions": 3
    }
  ],
  "languages": [
    {
      "id": "MDg6TGFuZ3VhZ2UxNDA=",
      "name": "JavaScript",
      "color": "#f1e05a"
    },
    {
      "id": "MDg6TGFuZ3VhZ2U2MDU=",
      "name": "SCSS",
      "color": "#c6538c"
    }
  ],
  "screenshots": [],
  "license": null
}