{
  "projectFullName": "newrelic-experimental/caos-ansible-roles",
  "issues": {
    "open": 3
  },
  "releases": 0,
  "latestRelease": null,
  "commits": 12,
  "lastSixMonthsCommitTotal": 5,
  "contributors": 3,
  "pullRequests": {
    "open": 0
  },
  "searchCategory": "good first issue",
  "cachedIssues": [],
  "cachedContributors": [
    {
      "id": 15685307,
      "login": "cristianciutea",
      "avatarUrl": "https://avatars.githubusercontent.com/u/15685307?v=4",
      "htmlUrl": "https://github.com/cristianciutea",
      "contributions": 3
    },
    {
      "id": 33873530,
      "login": "rogercoll",
      "avatarUrl": "https://avatars.githubusercontent.com/u/33873530?v=4",
      "htmlUrl": "https://github.com/rogercoll",
      "contributions": 7
    },
    {
      "id": 3380451,
      "login": "rubenruizdegauna",
      "avatarUrl": "https://avatars.githubusercontent.com/u/3380451?v=4",
      "htmlUrl": "https://github.com/rubenruizdegauna",
      "contributions": 1
    }
  ],
  "languages": [
    {
      "id": "MDg6TGFuZ3VhZ2U3ODY=",
      "name": "Jinja",
      "color": "#a52a22"
    },
    {
      "id": "MDg6TGFuZ3VhZ2UxMzk=",
      "name": "Shell",
      "color": "#89e051"
    }
  ],
  "screenshots": [],
  "license": {
    "id": "MDc6TGljZW5zZTI=",
    "name": "Apache License 2.0",
    "spdxId": "Apache-2.0",
    "url": "http://choosealicense.com/licenses/apache-2.0/",
    "featured": true,
    "key": "apache-2.0"
  }
}