{
  "name": "video-core-js",
  "fullName": "newrelic/video-core-js",
  "slug": "newrelic-video-core-js",
  "owner": {
    "login": "newrelic",
    "type": "Organization"
  },
  "title": "New Relic Video Core - JavaScript",
  "supportUrl": "https://discuss.newrelic.com/t/video-core-js-tracker/100303",
  "githubUrl": "https://github.com/newrelic/video-core-js",
  "permalink": "https://opensource.newrelic.com/projects/newrelic/video-core-js",
  "iconUrl": "https://github.com/newrelic/video-core-js/blob/master/icon.png?raw=true",
  "shortDescription": "Instrument the videos players",
  "description": "Core library for all New Relic Browser video trackers",
  "ossCategory": "community-project",
  "projectTags": ["lib", "video"],
  "primaryLanguage": "JavaScript",
  "acceptsContributions": true,
  "website": {
    "title": "New Relic Video Core - JavaScript",
    "url": "https://github.com/newrelic/video-core-js"
  }
}
