{
  "name": "insights-about-pagerduty",
  "fullName": "newrelic/insights-about-pagerduty",
  "slug": "newrelic-insights-about-pagerduty",
  "owner": {
    "login": "newrelic",
    "type": "Organization"
  },
  "title": "insights about-pagerduty",
  "supportUrl": "https://discuss.newrelic.com/",
  "githubUrl": "https://github.com/newrelic/insights-about-pagerduty",
  "permalink": "https://opensource.newrelic.com/projects/newrelic/insights-about-pagerduty",
  "iconUrl": "https://github.com/newrelic/insights-about-pagerduty/blob/master/icon.png?raw=true",
  "shortDescription": "",
  "description": "Slurp resolved PagerDuty incident data into New Relic Insights",
  "ossCategory": "tbd",
  "primaryLanguage": "Ruby",
  "projectTags": [ "nr1-app" ],
  "website": {
    "title": "insights about-pagerduty",
    "url": "https://github.com/newrelic/insights-about-pagerduty"
  },
  "version": "0.1.0"
}